{
  "link": "https://gofood.co.id/jakarta/restaurant/kfc-kemang-pratama-ef8c2c3e-61d6-4bd4-b9fa-10cfd6358dcf",
  "domain": "gofood.co.id",
  "tags": [
    "Cepat saji",
    "gofood.co.id"
  ],
  "crawling_time": "2024-01-13 21:19:21.062803",
  "crawling_time_epoch": 1705155561,
  "path_data_raw": "data/jakarta/bekasi-restaurants/KFC_Kemang_Pratama/json/e5eb6139-3832-4dd6-b4f8-2f0207dee3c0.json",
  "path_data_clean": "data/jakarta/bekasi-restaurants/KFC_Kemang_Pratama/json/e5eb6139-3832-4dd6-b4f8-2f0207dee3c0.json",
  "reviews_name": "KFC, Kemang Pratama",
  "location_review": "jakarta",
  "location_restaurant": {
    "city": "jakarta",
    "area": "bekasi-restaurants",
    "distance_km": 0.53
  },
  "range_prices": "40k-100k",
  "restaurant_id": "ef8c2c3e-61d6-4bd4-b9fa-10cfd6358dcf",
  "category_reviews": "food & baverage",
  "reviews_rating": {
    "total_ratings": {
      "average": 4.8,
      "total": 24067
    },
    "detail_total_rating": [
      {
        "score_rating": 2021,
        "category_rating": "taste"
      },
      {
        "score_rating": 1696,
        "category_rating": "portion"
      },
      {
        "score_rating": 1631,
        "category_rating": "packaging"
      }
    ]
  },
  "detail_reviews": {
    "username_id": "e5eb6139-3832-4dd6-b4f8-2f0207dee3c0",
    "username_reviews": "Imel",
    "initialName": "I",
    "image_reviews": null,
    "created_time": "2022-04-15T13:42:53.207485+07:00",
    "created_time_epoch": 1650030173,
    "reviews_rating": 2,
    "orders": {
      "orderedAt": "2022-04-15T05:47:43.418812Z",
      "items": [
        {
          "id": "d514292f-531b-412f-b692-4e34436f7ce7",
          "name": "Crispy Chicken"
        },
        {
          "id": "d5b0d07a-65fd-43a9-9535-47c2804bac2f",
          "name": "Original Chicken"
        }
      ]
    },
    "tags_review": [
      "CANNED_RESPONSE_ORDER",
      "gofood.co.id"
    ],
    "content_reviews": "oesen 1 ori 1 spicy.\ndikasih keduanya spicy. anak saya ngambek makan",
    "date_of_experience": ""
  }
}