{
  "link": "https://gofood.co.id/jakarta/restaurant/sate-madura-cak-ari-bekasi-selatan-65c0efa7-65ff-4868-95e5-a4ec690c6c14",
  "domain": "gofood.co.id",
  "tags": [
    "Sate",
    "gofood.co.id"
  ],
  "crawling_time": "2024-01-13 22:35:33.625561",
  "crawling_time_epoch": 1705160133,
  "path_data_raw": "data/jakarta/bekasi-restaurants/Sate_Madura_Cak_Ari_Bekasi_Selatan/json/1d762879-6695-4fca-b677-2a6d312d4f80.json",
  "path_data_clean": "data/jakarta/bekasi-restaurants/Sate_Madura_Cak_Ari_Bekasi_Selatan/json/1d762879-6695-4fca-b677-2a6d312d4f80.json",
  "reviews_name": "Sate Madura Cak Ari, Bekasi Selatan",
  "location_review": "jakarta",
  "location_restaurant": {
    "city": "jakarta",
    "area": "bekasi-restaurants",
    "distance_km": 0.69
  },
  "range_prices": "40k-100k",
  "restaurant_id": "65c0efa7-65ff-4868-95e5-a4ec690c6c14",
  "category_reviews": "food & baverage",
  "reviews_rating": {
    "total_ratings": {
      "average": 4.7,
      "total": 6478
    },
    "detail_total_rating": [
      {
        "score_rating": 827,
        "category_rating": "taste"
      },
      {
        "score_rating": 589,
        "category_rating": "portion"
      },
      {
        "score_rating": 535,
        "category_rating": "packaging"
      }
    ]
  },
  "detail_reviews": {
    "username_id": "1d762879-6695-4fca-b677-2a6d312d4f80",
    "username_reviews": "Astri C.",
    "initialName": "AC",
    "image_reviews": null,
    "created_time": "2022-07-28T08:01:38.623298+07:00",
    "created_time_epoch": 1658995298,
    "reviews_rating": 2,
    "orders": {
      "orderedAt": "2022-07-27T13:40:42.051307Z",
      "items": [
        {
          "id": "6d91bf19-4b0b-4a41-a89c-61fe4914d258",
          "name": "Sate Kambing 15 Tusuk"
        },
        {
          "id": "4c057ee6-4854-4739-bbde-0d8d68f55d26",
          "name": "Sate Ayam 15  Tusuk"
        }
      ]
    },
    "tags_review": [
      "CANNED_RESPONSE_ORDER",
      "gofood.co.id"
    ],
    "content_reviews": "Untuk satenya memang sudah enak, tapi tolong tingkatkan lagi untuk ketepatan pesanan! saya sudah pesan 2 kali. yang pesanan pertama bumbunya ngga ada sama sekali, dan giliran pesanan kedua di tanggal 27 Juli, sate ayam yang saya pesan 15 tusuk, aktualnya yang datang cuma 5, sangat mengecewakan sekali. saya sudah chat driver untuk kembali menukar pesanan tapi sudah tidak bisa dihubungi. tolong kedepannya jangan sampai lalai lagi dalam menyiapkan pesanan pembeli. trimakasih",
    "date_of_experience": ""
  }
}