{
  "link": "https://gofood.co.id/jakarta/restaurant/mcdonald-s-pekayon-50150204-8f6d-4372-8458-668f1be126e8",
  "domain": "gofood.co.id",
  "tags": [
    "Cepat saji",
    "Sweets",
    "Jajanan",
    "gofood.co.id"
  ],
  "crawling_time": "2024-01-13 23:23:16.939446",
  "crawling_time_epoch": 1705162996,
  "path_data_raw": "data/jakarta/bekasi-restaurants/McDonalds_Pekayon/json/2198fb6a-3073-4764-906f-5bc197b1b8a5.json",
  "path_data_clean": "data/jakarta/bekasi-restaurants/McDonalds_Pekayon/json/2198fb6a-3073-4764-906f-5bc197b1b8a5.json",
  "reviews_name": "McDonald's, Pekayon",
  "location_review": "jakarta",
  "location_restaurant": {
    "city": "jakarta",
    "area": "bekasi-restaurants",
    "distance_km": 0.46
  },
  "range_prices": "40k-100k",
  "restaurant_id": "50150204-8f6d-4372-8458-668f1be126e8",
  "category_reviews": "food & baverage",
  "reviews_rating": {
    "total_ratings": {
      "average": 4.8,
      "total": 70397
    }
  },
  "detail_total_rating": [
    {
      "category_rating": "taste",
      "score_rating": 4555
    },
    {
      "category_rating": "packaging",
      "score_rating": 3695
    },
    {
      "category_rating": "freshness",
      "score_rating": 3669
    }
  ],
  "detail_reviews": {
    "username_id": "2198fb6a-3073-4764-906f-5bc197b1b8a5",
    "username_reviews": "O***** R****",
    "initialName": "OR",
    "image_reviews": null,
    "created_time": "2022-03-22T23:14:41.708901+07:00",
    "created_time_epoch": 1647990881,
    "reviews_rating": 2,
    "orders": {
      "orderedAt": "2022-03-22T15:17:49.239997Z",
      "items": [
        {
          "id": "567db9ae-9405-4f61-8d44-09cab6ba28ef",
          "name": "PaHeBat Cheeseburger with Egg, Medium"
        },
        {
          "id": "e78f00d1-20ba-4652-91a4-a03dc6a16e59",
          "name": "Paket Hemat Big Mac, Medium"
        },
        {
          "id": "e8822f07-3a0f-49fb-945f-71085413e6e2",
          "name": "Chicken Snack Wrap"
        }
      ]
    },
    "tags_review": [
      "gofood.co.id"
    ],
    "content_reviews": "French flys nya sedikit banget.",
    "date_of_experience": ""
  }
}