{
  "link": "https://gofood.co.id/jakarta/restaurant/mcdonald-s-pekayon-50150204-8f6d-4372-8458-668f1be126e8",
  "domain": "gofood.co.id",
  "tags": [
    "Cepat saji",
    "Sweets",
    "Jajanan",
    "gofood.co.id"
  ],
  "crawling_time": "2024-01-13 23:23:16.939446",
  "crawling_time_epoch": 1705162996,
  "path_data_raw": "data/jakarta/bekasi-restaurants/McDonalds_Pekayon/json/98962d13-c959-4dc6-9d7d-1e3a29ecab09.json",
  "path_data_clean": "data/jakarta/bekasi-restaurants/McDonalds_Pekayon/json/98962d13-c959-4dc6-9d7d-1e3a29ecab09.json",
  "reviews_name": "McDonald's, Pekayon",
  "location_review": "jakarta",
  "location_restaurant": {
    "city": "jakarta",
    "area": "bekasi-restaurants",
    "distance_km": 0.46
  },
  "range_prices": "40k-100k",
  "restaurant_id": "50150204-8f6d-4372-8458-668f1be126e8",
  "category_reviews": "food & baverage",
  "reviews_rating": {
    "total_ratings": {
      "average": 4.8,
      "total": 70397
    }
  },
  "detail_total_rating": [
    {
      "category_rating": "taste",
      "score_rating": 4555
    },
    {
      "category_rating": "packaging",
      "score_rating": 3695
    },
    {
      "category_rating": "freshness",
      "score_rating": 3669
    }
  ],
  "detail_reviews": {
    "username_id": "98962d13-c959-4dc6-9d7d-1e3a29ecab09",
    "username_reviews": "rina",
    "initialName": "R",
    "image_reviews": null,
    "created_time": "2022-02-21T18:52:45.069937+07:00",
    "created_time_epoch": 1645469565,
    "reviews_rating": 2,
    "orders": {
      "orderedAt": "2022-02-21T10:14:52.112737Z",
      "items": [
        {
          "id": "864aaee7-9e45-48ea-84ff-1550e82988e6",
          "name": "Fish Snack Wrap"
        },
        {
          "id": "6237dbd9-8b9c-4868-bd3a-a503144e5e7d",
          "name": "Rica Rica Fish Rice McD"
        },
        {
          "id": "d4d2e0a1-099c-4d22-b543-cc558bbc8985",
          "name": "White Choco Strawberry Pastry Pie"
        },
        {
          "id": "b6e2ada6-6488-4e52-b4c7-ac6cc6e1d7ff",
          "name": "Reusable Bag"
        },
        {
          "id": "6237dbd9-8b9c-4868-bd3a-a503144e5e7d",
          "name": "Rica Rica Fish Rice McD"
        }
      ]
    },
    "tags_review": [
      "CANNED_RESPONSE_PACKAGING",
      "CANNED_RESPONSE_TASTE",
      "gofood.co.id"
    ],
    "content_reviews": "Rica fishnya tumpah.. Berceceran...\nSeharusnya packing kertas coklatnya dipisah bagi jd 2 aja eh ini malah di tumpuk di jadiin satu semua pesenannya!\nTrus rasanya jg semuanya gak enak!\nPadahal dulu mcd pekayon ini yg rasanya pling enak dibnding cab mcd lainnya..\nChefnya ganti atau gmn nih?\nJd Kapok lah pesen disini",
    "date_of_experience": ""
  }
}