{
  "link": "https://gofood.co.id/jakarta/restaurant/mcdonald-s-pekayon-50150204-8f6d-4372-8458-668f1be126e8",
  "domain": "gofood.co.id",
  "tags": [
    "Cepat saji",
    "Sweets",
    "Jajanan",
    "gofood.co.id"
  ],
  "crawling_time": "2024-01-13 23:23:16.939446",
  "crawling_time_epoch": 1705162996,
  "path_data_raw": "data/jakarta/bekasi-restaurants/McDonalds_Pekayon/json/a4f9344e-0741-4cb1-b57c-90cc747bea1e.json",
  "path_data_clean": "data/jakarta/bekasi-restaurants/McDonalds_Pekayon/json/a4f9344e-0741-4cb1-b57c-90cc747bea1e.json",
  "reviews_name": "McDonald's, Pekayon",
  "location_review": "jakarta",
  "location_restaurant": {
    "city": "jakarta",
    "area": "bekasi-restaurants",
    "distance_km": 0.46
  },
  "range_prices": "40k-100k",
  "restaurant_id": "50150204-8f6d-4372-8458-668f1be126e8",
  "category_reviews": "food & baverage",
  "reviews_rating": {
    "total_ratings": {
      "average": 4.8,
      "total": 70397
    }
  },
  "detail_total_rating": [
    {
      "category_rating": "taste",
      "score_rating": 4555
    },
    {
      "category_rating": "packaging",
      "score_rating": 3695
    },
    {
      "category_rating": "freshness",
      "score_rating": 3669
    }
  ],
  "detail_reviews": {
    "username_id": "a4f9344e-0741-4cb1-b57c-90cc747bea1e",
    "username_reviews": "A**** R********",
    "initialName": "AR",
    "image_reviews": null,
    "created_time": "2020-03-06T09:30:01.032+07:00",
    "created_time_epoch": 1583487001,
    "reviews_rating": 5,
    "orders": {
      "orderedAt": "2020-03-06T01:54:15.781536Z",
      "items": [
        {
          "id": "2efaddfb-c9e1-46f6-92c5-df671c1242cc",
          "name": "PaMer 5 Spesial Medium"
        }
      ]
    },
    "tags_review": [
      "",
      "gofood.co.id"
    ],
    "content_reviews": "ko ayam yang 2 ga pedes min tapi di pict pedes",
    "date_of_experience": ""
  }
}