{
  "link": "https://gofood.co.id/jakarta/restaurant/domino-s-pizza-kemang-pratama-00fb7fae-fbe1-4b63-ad17-dc7094c64f9c",
  "domain": "gofood.co.id",
  "tags": [
    "Pizza & pasta",
    "Cepat saji",
    "Jajanan",
    "gofood.co.id"
  ],
  "crawling_time": "2024-01-13 21:54:55.611075",
  "crawling_time_epoch": 1705157695,
  "path_data_raw": "data/jakarta/bekasi-restaurants/Dominos_Pizza_Kemang_Pratama/json/120d610f-efe5-4c23-adf3-4c9a69db4c64.json",
  "path_data_clean": "data/jakarta/bekasi-restaurants/Dominos_Pizza_Kemang_Pratama/json/120d610f-efe5-4c23-adf3-4c9a69db4c64.json",
  "reviews_name": "Domino's Pizza, Kemang Pratama",
  "location_review": "jakarta",
  "location_restaurant": {
    "city": "jakarta",
    "area": "bekasi-restaurants",
    "distance_km": 0.47
  },
  "range_prices": "40k-100k",
  "restaurant_id": "00fb7fae-fbe1-4b63-ad17-dc7094c64f9c",
  "category_reviews": "food & baverage",
  "reviews_rating": {
    "total_ratings": {
      "average": 4.7,
      "total": 11582
    },
    "detail_total_rating": [
      {
        "score_rating": 1426,
        "category_rating": "taste"
      },
      {
        "score_rating": 1210,
        "category_rating": "portion"
      },
      {
        "score_rating": 1158,
        "category_rating": "packaging"
      }
    ]
  },
  "detail_reviews": {
    "username_id": "120d610f-efe5-4c23-adf3-4c9a69db4c64",
    "username_reviews": "M*******",
    "initialName": "M",
    "image_reviews": null,
    "created_time": "2020-03-22T17:47:40.343+07:00",
    "created_time_epoch": 1584899260,
    "reviews_rating": 1,
    "orders": {
      "orderedAt": "2020-03-22T09:53:44.768082Z",
      "items": [
        {
          "id": "80366da4-27f8-4831-bc82-043d7e98cb57",
          "name": "Large HT Premium Pizza Disc. 40%"
        }
      ]
    },
    "tags_review": [
      "CANNED_RESPONSE_PRICE",
      "gofood.co.id"
    ],
    "content_reviews": "pesanan tidak sesuaj di gambar menu",
    "date_of_experience": ""
  }
}