{
  "link": "https://gofood.co.id/jakarta/restaurant/richeese-factory-pekayon-fb7c3452-2cba-464a-9e24-23840a40a179",
  "domain": "gofood.co.id",
  "tags": [
    "Cepat saji",
    "Ayam & bebek",
    "Aneka nasi",
    "gofood.co.id"
  ],
  "crawling_time": "2024-01-13 22:35:35.688493",
  "crawling_time_epoch": 1705160135,
  "path_data_raw": "data/jakarta/bekasi-restaurants/Richeese_Factory_Pekayon/json/9b2fce57-195c-446f-b14c-81ee561ef776.json",
  "path_data_clean": "data/jakarta/bekasi-restaurants/Richeese_Factory_Pekayon/json/9b2fce57-195c-446f-b14c-81ee561ef776.json",
  "reviews_name": "Richeese Factory, Pekayon",
  "location_review": "jakarta",
  "location_restaurant": {
    "city": "jakarta",
    "area": "bekasi-restaurants",
    "distance_km": 0.97
  },
  "range_prices": "40k-100k",
  "restaurant_id": "fb7c3452-2cba-464a-9e24-23840a40a179",
  "category_reviews": "food & baverage",
  "reviews_rating": {
    "total_ratings": {
      "average": 4.7,
      "total": 32095
    },
    "detail_total_rating": [
      {
        "score_rating": 2029,
        "category_rating": "taste"
      },
      {
        "score_rating": 1477,
        "category_rating": "portion"
      },
      {
        "score_rating": 1469,
        "category_rating": "packaging"
      }
    ]
  },
  "detail_reviews": {
    "username_id": "9b2fce57-195c-446f-b14c-81ee561ef776",
    "username_reviews": "Y***** Y*****",
    "initialName": "YY",
    "image_reviews": null,
    "created_time": "2022-10-25T16:54:01.209772+07:00",
    "created_time_epoch": 1666716841,
    "reviews_rating": 2,
    "orders": {
      "orderedAt": "2022-10-25T09:03:11.98574Z",
      "items": [
        {
          "id": "2fb64133-69f5-4592-a6f3-c04c584a7f08",
          "name": "Combo Fire Drum Stick"
        },
        {
          "id": "184ca9ee-286e-457c-b663-c4819b12aec6",
          "name": "Combo Duo Fire Chicken"
        },
        {
          "id": "bd86031e-81c9-49cc-8c5b-9651f6381c3c",
          "name": "Richoco Ice Cream Cup"
        }
      ]
    },
    "tags_review": [
      "gofood.co.id"
    ],
    "content_reviews": "Gada saus keju nyaaa",
    "date_of_experience": ""
  }
}