{
  "link": "https://gofood.co.id/jakarta/restaurant/richeese-factory-pekayon-fb7c3452-2cba-464a-9e24-23840a40a179",
  "domain": "gofood.co.id",
  "tags": [
    "Cepat saji",
    "Ayam & bebek",
    "Aneka nasi",
    "gofood.co.id"
  ],
  "crawling_time": "2024-01-13 22:35:35.688493",
  "crawling_time_epoch": 1705160135,
  "path_data_raw": "data/jakarta/bekasi-restaurants/Richeese_Factory_Pekayon/json/bc9c31fa-6124-4d55-aaaa-c89b02bd4f5f.json",
  "path_data_clean": "data/jakarta/bekasi-restaurants/Richeese_Factory_Pekayon/json/bc9c31fa-6124-4d55-aaaa-c89b02bd4f5f.json",
  "reviews_name": "Richeese Factory, Pekayon",
  "location_review": "jakarta",
  "location_restaurant": {
    "city": "jakarta",
    "area": "bekasi-restaurants",
    "distance_km": 0.97
  },
  "range_prices": "40k-100k",
  "restaurant_id": "fb7c3452-2cba-464a-9e24-23840a40a179",
  "category_reviews": "food & baverage",
  "reviews_rating": {
    "total_ratings": {
      "average": 4.7,
      "total": 32095
    },
    "detail_total_rating": [
      {
        "score_rating": 2029,
        "category_rating": "taste"
      },
      {
        "score_rating": 1477,
        "category_rating": "portion"
      },
      {
        "score_rating": 1469,
        "category_rating": "packaging"
      }
    ]
  },
  "detail_reviews": {
    "username_id": "bc9c31fa-6124-4d55-aaaa-c89b02bd4f5f",
    "username_reviews": "D***",
    "initialName": "D",
    "image_reviews": null,
    "created_time": "2022-07-22T19:24:59.850878+07:00",
    "created_time_epoch": 1658517899,
    "reviews_rating": 1,
    "orders": {
      "orderedAt": "2022-07-22T11:32:59.302525Z",
      "items": [
        {
          "id": "2fb64133-69f5-4592-a6f3-c04c584a7f08",
          "name": "Combo Fire Drum Stick"
        },
        {
          "id": "4141083f-15b3-4173-9e5d-3f4b56647c5b",
          "name": "Fire Chicken 1 Pcs"
        },
        {
          "id": "dbe4980b-17af-4781-bdfe-599f5b019afc",
          "name": "Pink Lava"
        },
        {
          "id": "b26efe77-2d23-4ef2-8760-5d41d8d7c14e",
          "name": "Fire Wedges"
        }
      ]
    },
    "tags_review": [
      "gofood.co.id"
    ],
    "content_reviews": "lagi Errrorrrrrrr pelayannya kayanya",
    "date_of_experience": ""
  }
}